{
    "events:title":
    {
        "title": "things:name",
        "datetime_local": "events:startDate",
        "type": "events:type",
        "url": "things:url",
        "image": "things:image",
        "venue":
        {
            "class_name": "locations",
            "city_name": "things:name",
            "lat": "geoCoordinates:latitude",
            "lon": "geoCoordinates:longitude",
            "postal_code": "postalAddresses:postalCode",
            "address": "postalAddresses:streetAddress"
        },
        "stats":
        {
            "class_name": "offers",
            "average_price": "offers:price"
        },
        "performers:name":
        {
            "class_name": "organizations",
            "name": "things:name"
        }
    }
}